[
    {
        "id": 0,
        "categoria": "vencidos",
        "produtos": []
    },
    {
        "id": 1,
        "categoria": "nenhuma",
        "produtos": []
    },
    {
        "id": 2,
        "categoria": "frutas",
        "produtos": [
            {
                "id": 0,
                "id_categoria": 2,
                "nome": "Ma\u00e7a",
                "marca": "Aurora",
                "preco": 5.99,
                "quantidade": [
                    [
                        "14/09/2025",
                        35
                    ]
                ],
                "id_fornecedor": 0
            },
            {
                "id": 1,
                "id_categoria": 2,
                "nome": "Banana Nanica Cacho",
                "marca": "Sadia",
                "preco": 3.99,
                "quantidade": [
                    [
                        "14/09/2025",
                        390
                    ]
                ],
                "id_fornecedor": 0
            }
        ]
    }
]